optimi_lab/__init__.py
optimi_lab/__version__.py
optimi_lab/optimizer.py
optimi_lab/plot.py
optimi_lab/sensitivity_analysis.py
optimi_lab/intelligent_algorithm/__init__.py
optimi_lab/intelligent_algorithm/intelligent_algorithm_base.py
optimi_lab/intelligent_algorithm/mode_algorithm.py
optimi_lab/intelligent_algorithm/moead_algorithm.py
optimi_lab/intelligent_algorithm/mopso_algorithm.py
optimi_lab/intelligent_algorithm/nsga2_algorithm.py
optimi_lab/intelligent_algorithm/nsga3_algorithm.py
optimi_lab/intelligent_algorithm/utils.py
optimi_lab/intelligent_algorithm/operators/__init__.py
optimi_lab/intelligent_algorithm/operators/crossover.py
optimi_lab/intelligent_algorithm/operators/mutation.py
optimi_lab/intelligent_algorithm/operators/pso_operators.py
optimi_lab/intelligent_algorithm/operators/selection.py
optimi_lab/object_function/__init__.py
optimi_lab/object_function/utils.py
optimi_lab/surrogate_model/__init__.py
optimi_lab/surrogate_model/bagging.py
optimi_lab/surrogate_model/decision_tree_regression.py
optimi_lab/surrogate_model/extra_regression.py
optimi_lab/surrogate_model/k_nearest_neighbors.py
optimi_lab/surrogate_model/kriging.py
optimi_lab/surrogate_model/lasso_regression.py
optimi_lab/surrogate_model/mixture_surrogate_model.py
optimi_lab/surrogate_model/mlp_regression.py
optimi_lab/surrogate_model/polynomial_regression.py
optimi_lab/surrogate_model/random_forest.py
optimi_lab/surrogate_model/ridge_regression.py
optimi_lab/surrogate_model/surrogate_model_base.py
optimi_lab/surrogate_model/utils.py
optimi_lab/utils/__init__.py
optimi_lab/utils/config.py
optimi_lab/utils/exceptions.py
optimi_lab/utils/file_io.py
optimi_lab/utils/logger.py
optimi_lab/utils/multiprocessing.py
optimi_lab/utils/quantities.py
optimi_lab/utils/variable_space.py
optimi_lab/utils/visualization.py
optimi_lab-0.1.1.dist-info/METADATA
optimi_lab-0.1.1.dist-info/WHEEL
optimi_lab-0.1.1.dist-info/top_level.txt
optimi_lab-0.1.1.dist-info/RECORD
