Metadata-Version: 2.4
Name: optimi_lab
Version: 0.1.1
Author-email: Mingyang Bao <mingyangbob@gmail.com>
Maintainer-email: Mingyang Bao <mingyangbob@gmail.com>
License: Apache-2.0
Requires-Python: >=3.12
Requires-Dist: rtoml
Requires-Dist: matplotlib
Requires-Dist: numpy
Requires-Dist: pint
Requires-Dist: pydantic
Requires-Dist: scikit-learn
Requires-Dist: scipy
Requires-Dist: pandas
Provides-Extra: dev
Requires-Dist: pytest; extra == "dev"
Requires-Dist: pytest-cov; extra == "dev"
Requires-Dist: pytest-mock; extra == "dev"
Requires-Dist: pytest-xdist; extra == "dev"
Requires-Dist: coverage[toml]; extra == "dev"
Requires-Dist: pdoc; extra == "dev"
Requires-Dist: commitizen; extra == "dev"
Requires-Dist: pre-commit; extra == "dev"
Requires-Dist: ruff; extra == "dev"
